[
    {
        "id": "19",
        "B": 3.7935
    },
    {
        "id": "3",
        "B": 51.3758
    },
    {
        "id": "8",
        "B": 9.1441
    },
    {
        "id": "18",
        "B": 1942546446.69
    },
    {
        "id": "45",
        "B": 555094.84
    },
    {
        "id": "95",
        "B": 1.6727
    },
    {
        "id": "114",
        "B": 35.8424
    },
    {
        "id": "1416001",
        "B": 2156314358.21
    },
    {
        "id": "1403100",
        "B": 197730936.49
    },
    {
        "id": "1416111",
        "B": 5570599.48
    },
    {
        "id": "1426401",
        "B": 1383440139.21
    },
    {
        "id": "1402100",
        "B": 197175841.65
    },
    {
        "id": "1200100",
        "B": 5296077952.61
    },
    {
        "id": "1300100",
        "B": 5012432513.01
    },
    {
        "id": "1100100",
        "B": 10308510465.62
    }
]